a_cv_sift_detection/LICENSE
a_cv_sift_detection/README.MD
a_cv_sift_detection/__init__.py
a_cv_sift_detection/requirements.txt
a_cv_sift_detection/thirdparty.json
a_cv_sift_detection-0.10.dist-info/LICENSE.rst
a_cv_sift_detection-0.10.dist-info/METADATA
a_cv_sift_detection-0.10.dist-info/WHEEL
a_cv_sift_detection-0.10.dist-info/top_level.txt
a_cv_sift_detection-0.10.dist-info/RECORD
