Metadata-Version: 2.1
Name: a-cv-sift-detection
Version: 0.10
Summary: Detecting objects using openCV and sift
Home-page: https://github.com/hansalemaos/a_cv_sift_detection
Author: Johannes Fischer
Author-email: <aulasparticularesdealemaosp@gmail.com>
License: MIT
Keywords: opencv,cv2
Classifier: Development Status :: 4 - Beta
Classifier: Programming Language :: Python :: 3 :: Only
Classifier: Programming Language :: Python :: 3.9
Classifier: Topic :: Scientific/Engineering :: Visualization
Classifier: Topic :: Software Development :: Libraries :: Python Modules
Classifier: Topic :: Text Editors :: Text Processing
Classifier: Topic :: Text Processing :: General
Classifier: Topic :: Text Processing :: Indexing
Classifier: Topic :: Text Processing :: Filters
Classifier: Topic :: Utilities
License-File: LICENSE.rst
Requires-Dist: a-cv2-imshow-thread
Requires-Dist: a-cv-imwrite-imread-plus
Requires-Dist: a-pandas-ex-group-coordinates-by-distance
Requires-Dist: keyboard
Requires-Dist: kthread
Requires-Dist: opencv-python
Requires-Dist: pandas
Requires-Dist: Shapely
Requires-Dist: windows-adb-screen-capture
